IptcEditor/VERSION.rst
IptcEditor/__init__.py
IptcEditor/__main__.py
IptcEditor/resources/default.png
IptcEditor/resources/iptc_editor-128x128.png
IptcEditor/resources/iptc_editor-256x256.png
IptcEditor/resources/iptc_editor-512x512.png
IptcEditor/resources/iptceditor.glade
IptcEditor/resources/python-iptceditor-gtk3.desktop
IptcEditor/resources/web-browser.png
IptcEditor/src/__init__.py
IptcEditor/src/data_reader.py
IptcEditor/src/engine.py
IptcEditor/src/gui_gtk_glade.py
IptcEditor-0.4.2.4.dist-info/DESCRIPTION.rst
IptcEditor-0.4.2.4.dist-info/METADATA
IptcEditor-0.4.2.4.dist-info/RECORD
IptcEditor-0.4.2.4.dist-info/WHEEL
IptcEditor-0.4.2.4.dist-info/metadata.json
IptcEditor-0.4.2.4.dist-info/top_level.txt
