Metadata-Version: 2.0
Name: IptcEditor
Version: 0.4.2.4
Summary: Python3 GTK3 wrapper for EXIV2, which is used to read and edit image IPTC metadata. It can handle bulk operations on directories of image files.
Home-page: https://www.zaziork.com
Author: Dan Bright
Author-email: productions@zaziork.com
License: GNU General Public License v3 or later (GPLv3+)
Keywords: ITPC,image metadata editor,ITPC metadata editor
Platform: UNKNOWN
Classifier: Development Status :: 4 - Beta
Classifier: Intended Audience :: End Users/Desktop
Classifier: Natural Language :: English
Classifier: License :: OSI Approved :: GNU General Public License v3 or later (GPLv3+)
Classifier: Operating System :: Unix
Classifier: Programming Language :: Python
Classifier: Programming Language :: Python :: 3
Classifier: Programming Language :: Python :: 3.3
Classifier: Programming Language :: Python :: 3.4
Classifier: Programming Language :: Python :: 3.5
Classifier: Topic :: Utilities
Requires-Dist: datetime
